{
  "filters": [
    {
      "id": "all",
      "label": "Összes",
      "type": "all"
    },
    {
      "id": "work",
      "label": "Munka",
      "type": "category",
      "categories": [
        "work"
      ]
    },
    {
      "id": "social",
      "label": "Közösségi média",
      "type": "category",
      "categories": [
        "social"
      ]
    },
    {
      "id": "watch",
      "label": "Videóplatform",
      "type": "category",
      "categories": [
        "watch"
      ]
    },
    {
      "id": "dev",
      "label": "Fejlesztés",
      "type": "category",
      "categories": [
        "dev"
      ]
    },
    {
      "id": "support",
      "label": "Támogatás",
      "type": "category",
      "categories": [
        "support"
      ]
    },
    {
      "id": "links",
      "label": "Linkgyűjtők",
      "type": "category",
      "categories": [
        "links"
      ]
    }
  ],
  "items": [
    {
      "id": "youtube-en",
      "url": "https://www.youtube.com/@KeresztesZsolti",
      "provider": "YouTube",
      "providerExtra": "EN",
      "category": "watch",
      "tags": [
        "english",
        "video-platform"
      ],
      "title": "Keresztes Zsolt - Vlog, Self-Dev, Science&Tech",
      "description": "Önfejlesztési és STEM tartalmak angol, román és német nyelven.",
      "icon": "youtube",
      "profileId": "@KeresztesZsolti",
      "highlightUrlIdentifier": true,
      "styles": {
        "badgeColor": "#ff0000",
        "iconScale": 1
      }
    },
    {
      "id": "youtube-hu",
      "url": "https://www.youtube.com/@KeresztesZsolt",
      "provider": "YouTube",
      "providerExtra": "HU",
      "category": "watch",
      "tags": [
        "hungarian",
        "video-platform"
      ],
      "title": "Keresztes Zsolt - Vlog,Önfejlesztés,Tudomány&Tech",
      "description": "Önfejlesztési és STEM tartalmak magyar nyelven.",
      "icon": "youtube",
      "profileId": "@KeresztesZsolt",
      "highlightUrlIdentifier": true,
      "styles": {
        "badgeColor": "#ff0000",
        "iconScale": 1
      }
    },
    {
      "id": "linkedin",
      "url": "https://www.linkedin.com/in/kereszteszsolt",
      "provider": "LinkedIn",
      "category": "work",
      "tags": [
        "professional",
        "social-media"
      ],
      "title": "Keresztes Zsolt",
      "description": "Szakmai profil. STEM, önfejlesztés és projektfrissítések.",
      "icon": "linkedin",
      "profileId": "kereszteszsolt",
      "segmentMark": 2,
      "highlightUrlIdentifier": true,
      "styles": {
        "badgeColor": "#0a66c2",
        "iconScale": 1.46
      }
    },
    {
      "id": "tiktok-en",
      "url": "https://www.tiktok.com/@kereszteszsoltie",
      "provider": "TikTok",
      "providerExtra": "EN",
      "category": "watch",
      "tags": [
        "english",
        "social-media",
        "video-platform"
      ],
      "title": "Keresztes Zsolt",
      "description": "Önfejlesztési és STEM tartalmak angol, román és német nyelven.",
      "icon": "tiktok",
      "profileId": "@kereszteszsoltie",
      "highlightUrlIdentifier": true,
      "styles": {
        "badgeColor": "#111111",
        "iconScale": 1.14
      }
    },
    {
      "id": "tiktok-hu",
      "url": "https://www.tiktok.com/@kereszteszsolti",
      "provider": "TikTok",
      "providerExtra": "HU",
      "category": "watch",
      "tags": [
        "hungarian",
        "social-media",
        "video-platform"
      ],
      "title": "Keresztes Zsolt",
      "description": "Önfejlesztési és STEM tartalmak magyar nyelven.",
      "icon": "tiktok",
      "profileId": "@kereszteszsolti",
      "highlightUrlIdentifier": true,
      "styles": {
        "badgeColor": "#111111",
        "iconScale": 1.14
      }
    },
    {
      "id": "x",
      "url": "https://x.com/KeresztesZsolti",
      "provider": "X",
      "providerExtra": "Twitter",
      "category": "social",
      "tags": [
        "social-media"
      ],
      "title": "Keresztes Zsolt",
      "description": "Szakmai profil. STEM, önfejlesztés és projektfrissítések.",
      "icon": "x",
      "profileId": "@KeresztesZsolti",
      "highlightUrlIdentifier": true,
      "styles": {
        "badgeColor": "#111111",
        "iconScale": 2
      }
    },
    {
      "id": "website-en",
      "url": "https://www.kereszteszsolt.com",
      "provider": "zsoltkeresztes.com",
      "category": "work",
      "tags": [
        "english",
        "website"
      ],
      "title": "Személyes weboldal (EN)",
      "description": "Keresztes Zsolt személyes weboldala angol nyelvű tartalommal.",
      "icon": "website",
      "profileId": "kereszteszsolt.com",
      "highlightUrlIdentifier": true,
      "styles": {
        "badgeColor": "#3d2a21",
        "iconScale": 1.22
      }
    },
    {
      "id": "website-hu",
      "url": "https://www.kereszteszsolt.hu",
      "provider": "kereszteszsolt.hu",
      "category": "work",
      "tags": [
        "hungarian",
        "website"
      ],
      "title": "Személyes weboldal (HU)",
      "description": "Keresztes Zsolt személyes weboldala magyar nyelvű tartalommal.",
      "icon": "website",
      "profileId": "kereszteszsolt.hu",
      "highlightUrlIdentifier": true,
      "styles": {
        "badgeColor": "#3d2a21",
        "iconScale": 1.22
      }
    },
    {
      "id": "support",
      "url": "https://buymeacoffee.com/kereszteszsolt",
      "provider": "Buy Me A Coffee",
      "category": "support",
      "tags": [
        "support"
      ],
      "title": "Támogasd a munkámat",
      "description": "Támogasd a munkámat, ha értékesnek találod.",
      "icon": "support",
      "profileId": "kereszteszsolt",
      "highlightUrlIdentifier": true,
      "styles": {
        "badgeColor": "#ffdd00",
        "iconScale": 1.12
      }
    },
    {
      "id": "focus-guard",
      "url": "https://chromewebstore.google.com/detail/focus-guard/bdfnblnbjckkhknignkpmckeelfplill",
      "provider": "Focus Guard",
      "category": "dev",
      "tags": [
        "english",
        "dev"
      ],
      "title": "Focus Guard",
      "description": "Chrome-bővítmény, amely fókuszüzenettel blokkolja a zavaró weboldalakat.",
      "icon": "/icons/focus-guard-shield.svg",
      "profileId": "bdfnblnbjckkhknignkpmckeelfplill",
      "highlightUrlIdentifier": true,
      "styles": {
        "badgeColor": "#4b7a63",
        "badge1Color": "#38584a",
        "iconScale": 1.28
      }
    },
    {
      "id": "link-collection-en",
      "url": "https://zsoltkeresztes.com",
      "provider": "zsoltkeresztes.com",
      "category": "links",
      "tags": [
        "english",
        "link-hub"
      ],
      "title": "Egyedi linkgyűjtemény (EN)",
      "description": "Angol nyelvű linkgyűjteményes weboldal.",
      "icon": "website",
      "profileId": "zsoltkeresztes.com",
      "highlightUrlIdentifier": true,
      "styles": {
        "badgeColor": "#5b3a29",
        "iconScale": 1.22
      }
    },
    {
      "id": "link-collection-hu",
      "url": "https://www.zsoltkeresztes.hu",
      "provider": "zsoltkeresztes.hu",
      "category": "links",
      "tags": [
        "hungarian",
        "link-hub"
      ],
      "title": "Egyedi linkgyűjtemény (HU)",
      "description": "Magyar nyelvű linkgyűjteményes weboldal.",
      "icon": "website",
      "profileId": "zsoltkeresztes.hu",
      "highlightUrlIdentifier": true,
      "styles": {
        "badgeColor": "#5b3a29",
        "iconScale": 1.22
      }
    },
    {
      "id": "github",
      "url": "https://github.com/kereszteszsolt",
      "provider": "GitHub",
      "category": "dev",
      "tags": [
        "code",
        "dev"
      ],
      "title": "Keresztes Zsolt",
      "description": "Kódtárolók és projektek.",
      "icon": "github",
      "profileId": "kereszteszsolt",
      "highlightUrlIdentifier": true,
      "styles": {
        "badgeColor": "#181717",
        "iconScale": 1.22
      }
    },
    {
      "id": "project-collection",
      "url": "https://kereszteszsolt.net",
      "provider": "kereszteszsolt.net",
      "category": "dev",
      "tags": [
        "code",
        "dev",
        "website"
      ],
      "title": "Projektgyűjtemény",
      "description": "Keresztes Zsolt GitHubon elérhető projektgyűjteménye válogatott projektekkel és előnézetekkel.",
      "icon": "website",
      "profileId": "kereszteszsolt.net",
      "highlightUrlIdentifier": true,
      "styles": {
        "badgeColor": "#181717",
        "iconScale": 1.22
      }
    },
    {
      "id": "facebook",
      "url": "https://www.facebook.com/KeresztesZsolt.kzs",
      "provider": "Facebook",
      "category": "social",
      "tags": [
        "social-media"
      ],
      "title": "Keresztes Zsolt",
      "description": "Szakmai Facebook-oldal. STEM, önfejlesztés és projektfrissítések.",
      "icon": "facebook",
      "profileId": "KeresztesZsolt.kzs",
      "highlightUrlIdentifier": true,
      "styles": {
        "badgeColor": "#1877F2",
        "iconScale": 1.22
      }
    },
    {
      "id": "instagram",
      "url": "https://www.instagram.com/kereszteszsolt_kzs",
      "provider": "Instagram",
      "category": "social",
      "tags": [
        "social-media"
      ],
      "title": "Keresztes Zsolt",
      "description": "Telefonnal készült fotók, növények, bogarak, madarak és más apró pillanatok.",
      "icon": "instagram",
      "profileId": "@kereszteszsolt_kzs",
      "highlightUrlIdentifier": true,
      "styles": {
        "badgeColor": "#E4405F",
        "iconScale": 1.2
      }
    },
    {
      "id": "linktree",
      "url": "https://linktr.ee/kereszteszsolt",
      "provider": "Linktree",
      "providerExtra": "",
      "category": "links",
      "tags": [
        "link-hub"
      ],
      "title": "Linktree összes link",
      "description": "Linktree linkgyűjtemény.",
      "icon": "linktree",
      "profileId": "kereszteszsolt",
      "highlightUrlIdentifier": true,
      "styles": {
        "badgeColor": "#2bb673",
        "iconScale": 1.18
      }
    }
  ]
}
